tidal_unofficial/__init__.py
tidal_unofficial/tidal.py
tidal_unofficial-0.1.0.dist-info/LICENSE
tidal_unofficial-0.1.0.dist-info/METADATA
tidal_unofficial-0.1.0.dist-info/WHEEL
tidal_unofficial-0.1.0.dist-info/top_level.txt
tidal_unofficial-0.1.0.dist-info/RECORD
