Metadata-Version: 2.1
Name: tidal-unofficial
Version: 0.1.0
Summary: An unofficial library to use Tidal's API where the authorization is not required
Author: Lorenzo Bocchi
Author-email: lorenzobocchi99@yahoo.com
License: MIT
Project-URL: Homepage, https://github.com/bocchilorenzo/tidal_unofficial
Project-URL: Source, https://github.com/bocchilorenzo/tidal_unofficial
Project-URL: Documentation, https://tidal-unofficial.readthedocs.io/
Classifier: Intended Audience :: Developers
Classifier: License :: OSI Approved :: MIT License
Classifier: Programming Language :: Python
Classifier: Programming Language :: Python :: 3
Classifier: Programming Language :: Python :: 3.7
Classifier: Programming Language :: Python :: 3.8
Classifier: Programming Language :: Python :: 3.9
Classifier: Operating System :: OS Independent
License-File: LICENSE
Requires-Dist: requests
